visualsnoop/__init__.py
visualsnoop/auth.py
visualsnoop/exceptions.py
visualsnoop/models.py
visualsnoop-0.2.dist-info/DESCRIPTION.rst
visualsnoop-0.2.dist-info/METADATA
visualsnoop-0.2.dist-info/metadata.json
visualsnoop-0.2.dist-info/RECORD
visualsnoop-0.2.dist-info/top_level.txt
visualsnoop-0.2.dist-info/WHEEL
