Metadata-Version: 2.0
Name: visualsnoop
Version: 0.2
Summary: VisualSnoop Client module for Python
Home-page: https://github.com/visualsnoop/visualsnoop-client-python
Author: Janoš Guljaš
Author-email: janos@visualsnoop.com
License: BSD
Keywords: VisualSnoop image search Python client HTTP RESTful
Platform: UNKNOWN
Classifier: Development Status :: 4 - Beta
Classifier: Environment :: Console
Classifier: Intended Audience :: Developers
Classifier: License :: OSI Approved :: BSD License
Classifier: Topic :: Internet :: WWW/HTTP :: Indexing/Search
Classifier: Topic :: Scientific/Engineering :: Image Recognition
Classifier: Topic :: Software Development :: Libraries :: Python Modules
Classifier: Programming Language :: Python :: 2
Classifier: Programming Language :: Python :: 2.7
Classifier: Programming Language :: Python :: 3
Classifier: Programming Language :: Python :: 3.3
Classifier: Programming Language :: Python :: 3.4
Requires-Dist: six (>=1.9.0)
Requires-Dist: requests (>=2.5.1)
Provides-Extra: docs
Requires-Dist: sphinx; extra == 'docs'
Requires-Dist: sphinx-rtd-theme; extra == 'docs'
